MANIFEST.in
README.md
requirements.txt
setup.py
epoxy/__init__.py
epoxy/component.py
epoxy/configuration.py
epoxy/core.py
epoxy/settings.py
epoxy/utils.py
epoxy.egg-info/PKG-INFO
epoxy.egg-info/SOURCES.txt
epoxy.egg-info/dependency_links.txt
epoxy.egg-info/requires.txt
epoxy.egg-info/top_level.txt
epoxy/test/__init__.py
epoxy/test/test_component.py
epoxy/test/test_configuration.py
epoxy/test/test_core.py
epoxy/test/test_dependency_list.py
epoxy/test/test_example_smsservice.py
epoxy/test/test_python_loader.py
epoxy/test/test_settings.py